cleanpandasdf/__init__.py
cleanpandasdf/dataframe.py
cleanpandasdf-0.1.3.dist-info/LICENSE
cleanpandasdf-0.1.3.dist-info/METADATA
cleanpandasdf-0.1.3.dist-info/WHEEL
cleanpandasdf-0.1.3.dist-info/top_level.txt
cleanpandasdf-0.1.3.dist-info/RECORD
