Metadata-Version: 2.1
Name: cleanpandasdf
Version: 0.1.3
Summary: Effortlessly clean and optimize pandas dataframes with precision and ease.
Home-page: https://github.com/pypa/sampleproject
Author: Sijo Valayakkad Manikandan
Author-email: sijopkd@gmail.com
Project-URL: Bug Tracker, https://github.com/pypa/sampleproject/issues
Classifier: Programming Language :: Python :: 3
Classifier: License :: OSI Approved :: MIT License
Classifier: Operating System :: OS Independent
Requires-Python: >=3.6
License-File: LICENSE
